LICENSE
MANIFEST.in
README.md
setup.py
django_tickets.egg-info/PKG-INFO
django_tickets.egg-info/SOURCES.txt
django_tickets.egg-info/dependency_links.txt
django_tickets.egg-info/requires.txt
django_tickets.egg-info/top_level.txt
tickets/__init__.py
tickets/admin.py
tickets/forms.py
tickets/models.py
tickets/settings.py
tickets/urls.py
tickets/views.py
tickets/locale/de/LC_MESSAGES/django.mo
tickets/locale/de/LC_MESSAGES/django.po
tickets/locale/es/LC_MESSAGES/django.mo
tickets/locale/es/LC_MESSAGES/django.po
tickets/locale/fr/LC_MESSAGES/django.mo
tickets/locale/fr/LC_MESSAGES/django.po
tickets/locale/it/LC_MESSAGES/django.mo
tickets/locale/it/LC_MESSAGES/django.po
tickets/locale/nl/LC_MESSAGES/django.mo
tickets/locale/nl/LC_MESSAGES/django.po
tickets/locale/ru/LC_MESSAGES/django.mo
tickets/locale/ru/LC_MESSAGES/django.po
tickets/migrations/0001_initial.py
tickets/migrations/__init__.py
tickets/templates/tickets/ticket_create.html
tickets/templates/tickets/ticket_mydetail.html
tickets/templates/tickets/ticket_mylist.html
tickets/tests/__init__.py
tickets/tests/factories.py
tickets/tests/settings.py
tickets/tests/test_forms.py
tickets/tests/test_models.py