Metadata-Version: 1.0
Name: django-tickets
Version: 0.3.0
Summary: Reusable django application providing a generic support ticket system
Home-page: https://github.com/byteweaver/django-tickets
Author: akuryou
Author-email: contact@byteweaver.net
License: MIT License
Platform: UNKNOWN
